evo_featureflags_server-1.25.0.dist-info/METADATA
evo_featureflags_server-1.25.0.dist-info/WHEEL
evo_featureflags_server-1.25.0.dist-info/entry_points.txt
featureflags/__init__.py
featureflags/__main__.py
featureflags/alembic.py
featureflags/cli.py
featureflags/config.py
featureflags/errors.py
featureflags/graph/__init__.py
featureflags/graph/actions.py
featureflags/graph/constants.py
featureflags/graph/context.py
featureflags/graph/graph.py
featureflags/graph/metrics.py
featureflags/graph/proto_adapter.py
featureflags/graph/types.py
featureflags/graph/utils.py
featureflags/http/__init__.py
featureflags/http/api/__init__.py
featureflags/http/api/flags.py
featureflags/http/api/health.py
featureflags/http/app.py
featureflags/http/container.py
featureflags/http/db.py
featureflags/http/lifecycle.py
featureflags/http/repositories/__init__.py
featureflags/http/repositories/flags.py
featureflags/http/types.py
featureflags/logging.py
featureflags/metrics.py
featureflags/migrations/__init__.py
featureflags/migrations/env.py
featureflags/migrations/script.py.mako
featureflags/migrations/versions/1876f90b58e8_added_feature_values_tables.py
featureflags/migrations/versions/2fa54f8b55c1_cleaup_condition_checks.py
featureflags/migrations/versions/33ace31b89cc_changelog_added.py
featureflags/migrations/versions/4d42cf3d11de_added_created_and_reported_timestamps.py
featureflags/migrations/versions/69f91d9fab0f_add_condition_position_column.py
featureflags/migrations/versions/8df4e7dd1897_delete_changelog_on_flag_delete.py
featureflags/migrations/versions/94e4203113b0_removed_auth_session_user_column.py
featureflags/migrations/versions/__init__.py
featureflags/migrations/versions/a327a3ea7a5f_added_flags_and_values_name_idx.py
featureflags/migrations/versions/b3fbbe647373_init.py
featureflags/migrations/versions/cce98484f923_auth_user_table_added.py
featureflags/models.py
featureflags/protobuf/__init__.py
featureflags/protobuf/backend.proto
featureflags/protobuf/backend_pb2.py
featureflags/protobuf/graph.proto
featureflags/protobuf/graph_pb2.py
featureflags/protobuf/service.proto
featureflags/protobuf/service_grpc.py
evo_featureflags_server-1.25.0.dist-info/RECORD
