Metadata-Version: 2.1
Name: evo-featureflags-server
Version: 1.25.0
Summary: Feature flags server
Author-Email: "d.zakharchuk" <d.zakharchuk@smartweb.com.ua>, "m.kindritskiy" <m.kindritskiy@smartweb.com.ua>, Vladimir Magamedov <vladimir@magamedov.com>
License: MIT
Project-URL: Documentation, https://featureflags.readthedocs.io/en/latest/
Project-URL: Repository, https://github.com/evo-company/featureflags
Project-URL: Homepage, https://github.com/evo-company/featureflags
Requires-Python: >=3.11
Requires-Dist: grpclib==0.4.6
Requires-Dist: hiku==0.7.5
Requires-Dist: protobuf<4.0.0
Requires-Dist: sqlalchemy[mypy]==1.4.42
Requires-Dist: aiopg[sa]==1.4.0
Requires-Dist: psycopg2==2.9.7
Requires-Dist: graphql-core==3.2.3
Requires-Dist: prometheus-client==0.17.1
Requires-Dist: alembic==1.12.0
Requires-Dist: metricslog==0.1.3
Requires-Dist: pyyaml==6.0.1
Requires-Dist: pyjwt==2.8.0
Requires-Dist: ldap3==2.9.1
Requires-Dist: pydantic>=2.3.0
Requires-Dist: pydantic-settings>=2.0.3
Requires-Dist: setuptools==68.2.2
Requires-Dist: fastapi>=0.103.2
Requires-Dist: orjson>=3.9.8
Requires-Dist: uvloop>=0.17.0
Requires-Dist: httptools>=0.6.0
Requires-Dist: uvicorn[standart]>=0.23.2
Requires-Dist: typer>=0.9.0
Requires-Dist: jinja2>=3.1.2
Requires-Dist: dependency-injector>=4.41.0
Requires-Dist: grpcio>=1.59.0
Requires-Dist: prometheus-fastapi-instrumentator>=6.1.0
Provides-Extra: sentry
Requires-Dist: sentry-sdk[fastapi,grpcio]>=1.40.5; extra == "sentry"
